Futurapay/__init__.py
Futurapay/Sdk/Contract/GatewayInterface.py
Futurapay/Sdk/Enums/PaymentURL.py
Futurapay/Sdk/Gateway/Futurapay.py
Futurapay/Sdk/Utils/Encryptions.py
futurapay-0.3.4.dist-info/METADATA
futurapay-0.3.4.dist-info/WHEEL
futurapay-0.3.4.dist-info/top_level.txt
futurapay-0.3.4.dist-info/RECORD
