Metadata-Version: 2.1
Name: futurapay
Version: 0.3.4
Summary: A simple package for testing purposes
Home-page: https://github.com/Rohit-kumar-raja/pythonTestpackage.git
Author: Rohit kumar
Author-email: rohitk.techexactly@gmail.com
Classifier: Programming Language :: Python :: 3
Classifier: License :: OSI Approved :: MIT License
Classifier: Operating System :: OS Independent
Requires-Dist: cryptography
